datagif/__about__.py
datagif/__init__.py
datagif/datagif.py
datagif/utilities.py
datagif-0.1.1.dist-info/LICENSE
datagif-0.1.1.dist-info/METADATA
datagif-0.1.1.dist-info/WHEEL
datagif-0.1.1.dist-info/top_level.txt
datagif-0.1.1.dist-info/RECORD
