Metadata-Version: 2.1
Name: datagif
Version: 0.1.1
Summary: Make animated gifs out of multiple data plots.
Home-page: https://github.com/Matyasz/datagif
Author: Taylor Matyasz
Author-email: tjmatyasz@gmail.com
License: GNU GPLv3
Keywords: python,data,science,data science,animated,gif,matplotlib,seaborn,imageio
Platform: UNKNOWN
Classifier: Development Status :: 3 - Alpha
Classifier: Framework :: Flake8
Classifier: Framework :: Matplotlib
Classifier: Intended Audience :: Education
Classifier: Intended Audience :: Science/Research
Classifier: License :: OSI Approved :: GNU General Public License v3 (GPLv3)
Classifier: Natural Language :: English
Classifier: Environment :: MacOS X
Classifier: Operating System :: POSIX
Classifier: Operating System :: POSIX :: Linux
Classifier: Operating System :: Microsoft :: Windows
Classifier: Programming Language :: Python
Classifier: Programming Language :: Python :: 3
Classifier: Topic :: Artistic Software
Classifier: Topic :: Multimedia
Classifier: Topic :: Scientific/Engineering
Classifier: Topic :: Scientific/Engineering :: Visualization
Classifier: Topic :: Software Development :: Libraries
Requires-Dist: imageio
Requires-Dist: pandas
Requires-Dist: seaborn
Requires-Dist: matplotlib
Provides-Extra: dev
Requires-Dist: IPython ; extra == 'dev'
Requires-Dist: jupyter ; extra == 'dev'
Provides-Extra: docs
Provides-Extra: interactive
Requires-Dist: IPython ; extra == 'interactive'
Requires-Dist: jupyter ; extra == 'interactive'
Provides-Extra: test
